[{
  "img":"img/RecommendLesson/qiangdiao_small.jpg",
  "videoHref":"http://zzenglish.net/zzweb/mobile/active/qiangdiao.html",
  "classTitle":"腔调控英语发音矫正培训",
  "classTime":" 2015.6.15~7.10 20:00~21:00",
  "teachers":"任铄炜"
},
  {
    "img":"img/RecommendLesson/New-concept.jpg",
    "videoHref":"http://zzenglish.net/zzweb/mobile/active/yaoyao.html",
    "classTitle":"新概念第一册语法专项突破",
    "classTime":"2015.6.22~8.14 19:00 ~ 20:00",
    "teachers":"姚瑶"
  },
  {
    "img":"img/RecommendLesson/zhiye.jpg",
    "videoHref":"http://zzenglish.net/zzweb/mobile/active/zhiye.html",
    "classTitle":"职场英语 ",
    "classTime":" 2015.6.15~7.10 20:00~21:00",
    "teachers":"Aiyo"
  },{
  "img":"img/RecommendLesson/phonics.jpg",
  "videoHref":"http://zzenglish.net/zzweb/mobile/active/phonics.html",
  "classTitle":"自然拼读法",
  "classTime":"2015.6.2~6.27 20:00~21:00",
  "teachers":"于天天"
}]